{
  "resource_state": 2,
  "athlete": {
    "id": 23558655,
    "resource_state": 1
  },
  "name": "Afternoon Run",
  "distance": 6361.2,
  "moving_time": 2189,
  "elapsed_time": 2443,
  "total_elevation_gain": 29,
  "type": "Run",
  "sport_type": "Run",
  "workout_type": null,
  "device_name": "Garmin fēnix 6 Pro",
  "id": 14684264344,
  "start_date": "2025-06-03T15:18:17Z",
  "start_date_local": "2025-06-03T17:18:17Z",
  "timezone": "(GMT+01:00) Europe/Copenhagen",
  "utc_offset": 7200,
  "location_city": null,
  "location_state": null,
  "location_country": null,
  "achievement_count": 3,
  "kudos_count": 3,
  "comment_count": 0,
  "athlete_count": 1,
  "photo_count": 0,
  "map": {
    "id": "a14684264344",
    "polyline": "ybvrI}czkAINAZOJ[AUIM@SD_@?]NWBKAKFKd@UHGl@]A]WSCg@vBId@BHIz@Oz@Ad@Op@GP?HUnAYh@Gh@Mh@_@p@_@hAg@nAa@nAWl@M@e@PCBAd@KbAMf@Ov@MJK@[\\MRGDEAGGKq@ISk@m@o@gAGS?F[b@q@zDGh@S~@KX]rA[n@?NOr@w@tCSVOI}AaD_@c@WP_@t@W^S`BSNm@pBWp@W|BYZ[|@KJ@FETi@Ue@NE?eAg@g@QMKQIyAgBYq@a@YOQo@iAMDM|BIr@YvAW|@[x@a@d@u@h@u@|BO`@S\\Gn@eAxCY~@eBbEMRIDMZuAxDa@|@Op@g@x@Yv@a@j@[p@Uj@Ux@INQPK`@}@rBe@H_@XOhAi@lBMBEb@e@vAY~Ae@lAm@|@SLYZcBfDwCnCSNi@Nk@VW`AA^`@r@Xt@?TOZ_@d@i@v@o@x@a@`@CD@HHc@FIF@f@VDH@ZKD]X{@dAeA|BENeAnBHVk@fBETYj@Ip@TdAW~@k@zC[z@gArECPk@tA]AWDWTk@`@_@l@@R?BDCGRQVi@f@_An@q@p@ANI\\MDQKKD_@^GJQp@oBhCs@lCUn@On@[p@Od@_@~AMZq@x@]bCIdAm@bAIPo@fC?j@o@vC}@bCKr@Op@Gl@Mh@Uj@Qz@Sr@i@pAcAnEOj@Wn@iAfEWfA[x@]fAYvAI\\MX[h@Ud@IXi@`AORK^Qb@c@n@k@hAs@jAw@dBIBYGSD{AdA_@ZWJc@Zg@CkAb@c@b@c@XK?m@@c@GM@[CYH]De@Cu@Qa@B[GgADc@Gk@?YGi@[aAD_AIKp@?ZKHISCCWEWYq@qA}@?g@ZK[SG_@[g@MK@OOo@ME@IE[Da@Lo@X_@f@Ql@c@T_@K",
    "resource_state": 3,
    "summary_polyline": "ybvrI}czkAINAZOJ[AUIM@SD_@?]NWBKAKFKd@UHGl@]A]WSCg@vBId@BHIz@Oz@Ad@Op@GP?HUnAYh@Gh@Mh@_@p@_@hAg@nAa@nAWl@M@e@PCBAd@KbAMf@Ov@MJK@[\\MRGDEAGGKq@ISk@m@o@gAGS?F[b@q@zDGh@S~@KX]rA[n@?NOr@w@tCSVOI}AaD_@c@WP_@t@W^S`BSNm@pBWp@W|BYZ[|@KJ@FETi@Ue@NE?eAg@g@QMKQIyAgBYq@a@YOQo@iAMDM|BIr@YvAW|@[x@a@d@u@h@u@|BO`@S\\Gn@eAxCY~@eBbEMRIDMZuAxDa@|@Op@g@x@Yv@a@j@[p@Uj@Ux@INQPK`@}@rBe@H_@XOhAi@lBMBEb@e@vAY~Ae@lAm@|@SLYZcBfDwCnCSNi@Nk@VW`AA^`@r@Xt@?TOZ_@d@i@v@o@x@a@`@CD@HHc@FIF@f@VDH@ZKD]X{@dAeA|BENeAnBHVk@fBETYj@Ip@TdAW~@k@zC[z@gArECPk@tA]AWDWTk@`@_@l@@R?BDCGRQVi@f@_An@q@p@ANI\\MDQKKD_@^GJQp@oBhCs@lCUn@On@[p@Od@_@~AMZq@x@]bCIdAm@bAIPo@fC?j@o@vC}@bCKr@Op@Gl@Mh@Uj@Qz@Sr@i@pAcAnEOj@Wn@iAfEWfA[x@]fAYvAI\\MX[h@Ud@IXi@`AORK^Qb@c@n@k@hAs@jAw@dBIBYGSD{AdA_@ZWJc@Zg@CkAb@c@b@c@XK?m@@c@GM@[CYH]De@Cu@Qa@B[GgADc@Gk@?YGi@[aAD_AIKp@?ZKHISCCWEWYq@qA}@?g@ZK[SG_@[g@MK@OOo@ME@IE[Da@Lo@X_@f@Ql@c@T_@K"
  },
  "trainer": false,
  "commute": false,
  "manual": false,
  "private": false,
  "visibility": "everyone",
  "flagged": false,
  "gear_id": "g22495929",
  "start_latlng": [],
  "end_latlng": [],
  "average_speed": 2.906,
  "max_speed": 6.58,
  "average_cadence": 86.5,
  "average_temp": 25,
  "has_heartrate": true,
  "average_heartrate": 142.4,
  "max_heartrate": 165,
  "heartrate_opt_out": false,
  "display_hide_heartrate_option": true,
  "elev_high": 14.2,
  "elev_low": -1.2,
  "upload_id": 15669882933,
  "upload_id_str": "15669882933",
  "external_id": "garmin_ping_445252096219",
  "from_accepted_tag": false,
  "pr_count": 1,
  "total_photo_count": 0,
  "has_kudoed": false
}