{
  "resource_state": 2,
  "athlete": {
    "id": 23558655,
    "resource_state": 1
  },
  "name": "Riddarholmen - Lilla Essingen",
  "distance": 10358.5,
  "moving_time": 3506,
  "elapsed_time": 3536,
  "total_elevation_gain": 110.3,
  "type": "Run",
  "sport_type": "Run",
  "workout_type": null,
  "id": 3475739400,
  "start_date": "2017-09-02T08:02:26Z",
  "start_date_local": "2017-09-02T10:02:26Z",
  "timezone": "(GMT+01:00) Europe/Stockholm",
  "utc_offset": 7200,
  "location_city": null,
  "location_state": null,
  "location_country": null,
  "achievement_count": 0,
  "kudos_count": 0,
  "comment_count": 0,
  "athlete_count": 1,
  "photo_count": 0,
  "map": {
    "id": "a3475739400",
    "summary_polyline": "k_`iJ_~emB@NCPCq@]}AO_BSkAe@mDEg@?e@CQEKMEa@Fg@BSD{@Xy@?M@k@PQJi@`@OTGFQBw@Co@TM@GFIZ@`@d@vDH|A?t@IxB@f@EPOTkAnAsAh@_AVOAm@Ku@GU?SHQEc@?[Ca@DKE[i@GUC_@CIA@?f@BbA?~@JvABbAAZY`CCt@BrBAzFHhILhF?tCv@rQF|A@dAHrAPnJXhDHxFVfDBhAFpA@dA\\bFHtCLtBD|CNjDFd@DPd@r@Pd@Jp@PbBFNV^VbADb@@p@EHKHk@Ja@Ry@Ta@Va@Ps@b@qAZgC|Ao@d@u@r@qA`B}@|@eA|Am@n@i@~@wAzAoAhBgCvCy@lAcCtCuD~Ew@lAk@dA[d@GNY|@[h@IXo@bEWnCGvAA~@DbEBNX^Nl@R`@FHh@ZX\\d@nAt@~AXdALhAFzBIlERjCPdBRpALnAHd@XfAP`Bf@xBVxCt@jEd@vD@v@QtAEfA@z@NzE?j@_@dGWdBOxA?bAJjARlA\\hAx@~A|@bCn@|AnBrD`DtGnAjCl@`BJFB?@CCCAH\\c@RM\\GhAIrBJv@NzAR`@@f@AZGVKpAs@fAeAr@w@xAaC`AmAp@oAf@u@j@gAt@iAr@yAd@o@l@aAt@_AhAkBN]Ny@X}Bb@yEBoEG}D?s@Dm@Nk@Nu@@UEg@Qs@YeBQgCk@oFQq@MkAS{@UuBCk@FsADgCHi@Ri@Zm@Xs@`@o@b@eA`@u@H]f@yAf@sB\\mBR{@Fg@Xi@Pk@f@wCXs@NuATkARoAR}@T}Ar@yDp@sCjAqIFWNUBS@_@Ac@UkBEu@Au@@k@Hq@Rw@HuAH[p@_BDWAw@W}B?{@LQXYASBGBAD@FLmC{F_AmCqAkC}AaEmBsEq@kBEEIAHKVELYLIR?l@PN@ZGPMJQHYl@mCFg@Ci@[iAIkAa@cCOyDe@cEa@sH[cEI}Ci@yEEkAKw@EkABgG?mKC}@DcA?cBCi@O{AAw@JcA\\gBVkB?eAE_@Dm@Lo@^y@ZmBFaBCiA?_@He@\\i@Hc@@}AFw@HmBGWKSOQIAsAh@m@\\Q?a@LeANIACCCOBy@KeAEcBOgAEg@?uBIu@EMA@ABDN?FIV",
    "resource_state": 2
  },
  "trainer": false,
  "commute": false,
  "manual": false,
  "private": false,
  "visibility": "everyone",
  "flagged": false,
  "gear_id": null,
  "start_latlng": [
    59.32,
    18.06
  ],
  "end_latlng": [
    59.32,
    18.06
  ],
  "average_speed": 2.955,
  "max_speed": 5.5,
  "has_heartrate": true,
  "average_heartrate": 147.4,
  "max_heartrate": 166,
  "heartrate_opt_out": false,
  "display_hide_heartrate_option": true,
  "elev_high": 40.5,
  "elev_low": 11.6,
  "upload_id": 3711987350,
  "upload_id_str": "3711987350",
  "external_id": "activity.fit",
  "from_accepted_tag": false,
  "pr_count": 0,
  "total_photo_count": 0,
  "has_kudoed": false
}