{
  "resource_state": 2,
  "athlete": {
    "id": 23558655,
    "resource_state": 1
  },
  "name": "Frederiksberg - Rødovre",
  "distance": 14105.7,
  "moving_time": 4470,
  "elapsed_time": 4519,
  "total_elevation_gain": 35.3,
  "type": "Run",
  "sport_type": "Run",
  "workout_type": null,
  "id": 3475739585,
  "start_date": "2017-08-29T05:47:04Z",
  "start_date_local": "2017-08-29T07:47:04Z",
  "timezone": "(GMT+01:00) Europe/Copenhagen",
  "utc_offset": 7200,
  "location_city": null,
  "location_state": null,
  "location_country": null,
  "achievement_count": 7,
  "kudos_count": 0,
  "comment_count": 0,
  "athlete_count": 1,
  "photo_count": 0,
  "map": {
    "id": "a3475739585",
    "summary_polyline": "cq{rIcgpkAPQZcAT[A]w@qAYs@{CcDQKKHkBpD_BtBw@vAmAvCiApAW~@IfAiAnB}@vBc@p@u@`CC\\HTJH?JW\\Y`Au@zAg@fBIlAm@|BOx@MdBDNHA?GGDe@lAa@rA[l@_@~Au@zA[jBCj@OlAs@dBOz@u@~Ai@tCk@lAGb@?f@l@vE`A|Fj@vCfApEh@|@d@xA`AxBtAlBp@tBdBzD~@nChArBr@lBz@bBhAnCh@nB`@z@DdAvA~Gt@hF^|CXjADdCf@fEj@rIPbITrCLzEl@`Fx@fDTfBT^VHl@aAL@Fj@OdBBZJVTVdATz@dAt@d@fAdCzApCVlA~@`BXr@Hn@FnAr@|Bj@dCTvBx@pCh@fA`BzBh@\\`AlBtAvAfEdD|CjBdEtBn@j@|@lA`BtCjAhC`@vAp@|@n@^HXJrAd@j@C`@e@t@o@dBAf@`@xAj@pE`AjEv@fClAjBVp@Hr@BlAA`AIbAOt@Yn@}@hAiDrBoB|@e@`@g@p@uAjCcE`Eg@r@c@|@sAfEmAvCKn@Dp@h@fC~@|GTxCj@xCPNvGsDzCwEpB}BtCe@`EwBjCKpBY\\UzA}ApBiAZc@\\w@l@sCFo@JqPCoEFgFKkBYcB_BmEy@yDOYUMgIeAi@WyBkDyByEcAy@}@eAE]NC@MKa@iAu@s@w@w@aC_AwB_BiCkBgBwB}@eFwCwD}CcBsBw@yAu@o@GDMe@g@e@qBcE[{AEiAMq@_@iBs@yB]}B]}@u@cAeAyBe@aBkAeDq@a@q@i@}@Ye@k@I_@FuAEYWE_@ZQ@k@_AKkAKu@[_AMs@_@kDa@gGGeEk@gMQ}Be@eE_@oGgB_Ls@}Ca@gAU}Bi@kBqAkC[cAu@yAi@eBgAoBaAeCWgA[y@kBaEcAcAmB{Fs@}AsAwFo@cBUyB[eASoA@qCC_AFm@^eAfB}CVo@`AmEf@aBVsBh@iBv@{DP_@hADhCv@d@`A`@b@p@nAb@d@R?j@t@^VFZj@|@rAzA~A`AfANpBhB|@^\\Cb@uBZaCr@wCRsBj@qDHwAv@eBR{@H_AFiDPuBn@oDBaBFm@TaAx@cC\\cB^iAB[KaB?_@i@eA_BkAs@y@cAe@SN_@dAsAdBc@z@@B",
    "resource_state": 2
  },
  "trainer": false,
  "commute": false,
  "manual": false,
  "private": false,
  "visibility": "everyone",
  "flagged": false,
  "gear_id": null,
  "start_latlng": [
    55.69,
    12.54
  ],
  "end_latlng": [
    55.69,
    12.54
  ],
  "average_speed": 3.156,
  "max_speed": 6.8,
  "has_heartrate": true,
  "average_heartrate": 154.3,
  "max_heartrate": 187,
  "heartrate_opt_out": false,
  "display_hide_heartrate_option": true,
  "elev_high": 14.3,
  "elev_low": 8.1,
  "upload_id": 3711987489,
  "upload_id_str": "3711987489",
  "external_id": "activity.fit",
  "from_accepted_tag": false,
  "pr_count": 3,
  "total_photo_count": 0,
  "has_kudoed": false
}