{
  "resource_state": 2,
  "athlete": {
    "id": 23558655,
    "resource_state": 1
  },
  "name": "Frederiksberg - Islev",
  "distance": 17004.3,
  "moving_time": 4911,
  "elapsed_time": 4911,
  "total_elevation_gain": 68.7,
  "type": "Run",
  "sport_type": "Run",
  "workout_type": null,
  "id": 3475739441,
  "start_date": "2017-09-05T04:18:33Z",
  "start_date_local": "2017-09-05T06:18:33Z",
  "timezone": "(GMT+01:00) Europe/Copenhagen",
  "utc_offset": 7200,
  "location_city": null,
  "location_state": null,
  "location_country": null,
  "achievement_count": 16,
  "kudos_count": 0,
  "comment_count": 0,
  "athlete_count": 1,
  "photo_count": 0,
  "map": {
    "id": "a3475739441",
    "summary_polyline": "sr{rIiepkADXG\\u@bBa@xA[f@qA`DeAzEo@vBg@pC]pAIv@o@rBg@pEo@vBe@~BKbA[tASJWGqByAqAwAoBoAiAqA_@?o@jBa@xBoAvDo@xD]fC_AxAe@bCyExKcAtA_An@qBbD_CzCg@Z}A|A[j@Sx@}@z@cBpCeCzBkBnCk@rAKd@@VVf@CVOB_@SS@_Bz@WTaA~AkDbDyEhCaGtBmAr@O^G`@ApAB`AI`@ULyBAQNUj@q@xC]jCu@tBu@bEoAzEgAlFQj@}AzBqAdBq@n@_CzCmAhBmCrCcFhHwDjDy@lAa@|@aCvBcBxBwDrGyAbE}BtHA`@JbAn@vCZxBrAjGh@~CLZ^`@fDfLXh@x@v@lCxA\\h@Nt@Gh@o@vBa@`Dc@`CS`Be@xBo@~FeA~EGjBKpA}@nDm@~EsApEa@|DiB|IE~@@p@jAnId@bFdAjCV|@~AvMJ`@j@x@JjBb@|CX|@zAhBxDnDVb@B[LGP~@\\hAt@tDd@tAdBnCd@f@f@TzAVZv@l@`AfAxCV~AZ~@D`@B|ALh@j@t@fBCtFxItE|HlChGZFn@o@t@`@fDgBp@q@xAoCXkAXe@f@uBd@oEd@yBh@aBd@eCTyCHuELqBFMVCd@sAj@m@r@[rB`@xBNPKHu@FG~B?`Gw@~C`@nBj@\\CbAc@dBNb@Gr@a@jBaBrByBrBeBnC_DlBmBlDe@ZD^ZpAGvBo@n@@|@kAfBkBbDsEjBuBrDeDx@k@XG|CPbDGdBGxB]pEkDbD{BpEiB`@YZm@`FgN~AcBdByAdDiFbF{BvAkAz@sAb@gBL_CMgBa@eA{@mAY{@oAeF_BqKAs@fAwBD[EUq@o@WeBq@c@e@s@}@eC_AuBwBmDyAgA{Am@aDeB_EwCy@kA_BmAqA{Bg@]oA_B_B}Ca@kAKo@CyAuAkFe@cDu@eA}AmDwBaG{@a@o@{@kAa@qCkEI[GsAg@wB_@kC]eECwDu@}NmA_OOeCY{B_@mBUyBw@kESu@sA}CKq@Rs@HgA`AcBd@eC`A{Hx@cEN{BnCaRVqCx@eEv@oFZ}C@_@KUeBuAi@y@kBcBEi@AeDDs@h@uC~@mG\\sAJsAC[Sa@gAm@My@@w@PeBpAeHr@cFhAmFA[Ui@Ki@Sc@Ca@|A_D",
    "resource_state": 2
  },
  "trainer": false,
  "commute": false,
  "manual": false,
  "private": false,
  "visibility": "everyone",
  "flagged": false,
  "gear_id": null,
  "start_latlng": [
    55.69,
    12.54
  ],
  "end_latlng": [
    55.69,
    12.54
  ],
  "average_speed": 3.462,
  "max_speed": 4.9,
  "has_heartrate": true,
  "average_heartrate": 165.9,
  "max_heartrate": 182,
  "heartrate_opt_out": false,
  "display_hide_heartrate_option": true,
  "elev_high": 28.3,
  "elev_low": 7.9,
  "upload_id": 3711987270,
  "upload_id_str": "3711987270",
  "external_id": "activity.fit",
  "from_accepted_tag": false,
  "pr_count": 11,
  "total_photo_count": 0,
  "has_kudoed": false
}