{
  "resource_state": 2,
  "athlete": {
    "id": 23558655,
    "resource_state": 1
  },
  "name": "Bellahøj - Amagerbro",
  "distance": 13190.7,
  "moving_time": 4908,
  "elapsed_time": 4931,
  "total_elevation_gain": 53.5,
  "type": "Run",
  "sport_type": "Run",
  "workout_type": null,
  "id": 3475729148,
  "start_date": "2019-01-23T07:03:56Z",
  "start_date_local": "2019-01-23T08:03:56Z",
  "timezone": "(GMT+01:00) Europe/Copenhagen",
  "utc_offset": 3600,
  "location_city": null,
  "location_state": null,
  "location_country": null,
  "achievement_count": 6,
  "kudos_count": 0,
  "comment_count": 0,
  "athlete_count": 1,
  "photo_count": 0,
  "map": {
    "id": "a3475729148",
    "summary_polyline": "uh|rI}bkkADPL@v@g@RSLENDPh@r@xE\\rAx@pEDHLB`A]HFBJZ`CXzDTtBBz@NvAPtEDnBJ|AXrH^`FZnCJrAPX`@T\\n@nAhBbAhB^Pt@Nl@|@j@PNNf@|Ax@fBXfAr@`B|@`BXv@H`@JlAl@pBn@dDFdBLd@Vn@jBfD\\`@j@~@l@h@j@jAr@v@xEfEjFzCrCjAh@d@dApA`A|AlAtCz@xBj@|@`@Zz@Zt@l@X@h@KJDBh@x@|Bb@|AlBpDX`@XL|Gt@z@Vd@^NTjAlCz@xBRRn@DHLHRBj@IpAAfAF`FDI?m@DOJMRA`Dx@dExAPAx@a@b@I~Bb@jBh@`JJ`@LTNt@|AZ\\VRj@T|@OrBVJFL\\FF`@N|@n@RFJA^Yd@Cn@}@VOjCIhG\\j@RlAv@lAj@~@F`JeAJGBI@i@DOHKH@QCGWSeFKwAC}@KmAEqDG{A?q@QsCUyB?u@CuAOqTBuBEqB@gBNg@@SGWe@}@mA}CMc@Ii@CcADiKIiJ?qCDiAGu@Ow@KeA]kCc@uEWkB{@eIy@eKGwACyBQ}B_@{QUuGImIIcB@o@IsACcDUqGAwCGaBFw@E{AJs@MqAGuBBqAAe@OoBq@{Ci@mESuBE_AAmCW_IaAaHi@cFYeAGk@GmAEyCH{ICGIC}BJGKL{BHmCLuBBqCI_BBkCM}AHcABkA?s@Eo@Be@Gq@SgAAo@AoDJwDAeBFyEQyEQeAF?Di@LKN@^Zz@VH?DG@_@M{Ae@uJw@qHKmBk@wHEmA[eDg@cHEgAMiAi@eIe@gGI_BMkA[{JKeBM{ABYN]CQIU?IPc@HKXAPS^o@jAeBv@uA`AsAb@}@BOAYTKXk@H[B]?[ISJm@As@lAkBn@k@f@q@Fe@O}ADg@|AwCHSf@oE|@eFPwB?k@Wq@E_@?s@DuAEc@?OhAkCz@}Cd@gAR_Ab@}@`@wALs@JKRHJQb@gCRaCTwABmAEsAGi@MSe@Qg@[I[A_@L_CbAyJTqBd@iCTyBBk@@mAT}CF}EBIRUJUNcBJId@MXWnAcBl@wA{@qEYiAUi@e@y@m@u@{@w@o@WGO?o@HmCn@sF`@eC@u@E_@K[e@c@I_@GIw@]mBYa@OGOASD{@",
    "resource_state": 2
  },
  "trainer": false,
  "commute": false,
  "manual": false,
  "private": false,
  "visibility": "everyone",
  "flagged": false,
  "gear_id": null,
  "start_latlng": [
    55.69,
    12.51
  ],
  "end_latlng": [
    55.66,
    12.59
  ],
  "average_speed": 2.688,
  "max_speed": 4.4,
  "has_heartrate": true,
  "average_heartrate": 141.9,
  "max_heartrate": 165,
  "heartrate_opt_out": false,
  "display_hide_heartrate_option": true,
  "elev_high": 22.3,
  "elev_low": -1.9,
  "upload_id": 3711976278,
  "upload_id_str": "3711976278",
  "external_id": "activity.fit",
  "from_accepted_tag": false,
  "pr_count": 0,
  "total_photo_count": 0,
  "has_kudoed": false
}