{
  "resource_state": 2,
  "athlete": {
    "id": 23558655,
    "resource_state": 1
  },
  "name": "Lunch Run",
  "distance": 20705,
  "moving_time": 7862,
  "elapsed_time": 8382,
  "total_elevation_gain": 92,
  "type": "Run",
  "sport_type": "Run",
  "workout_type": null,
  "device_name": "Suunto 9",
  "id": 4711066200,
  "start_date": "2021-01-31T10:45:35Z",
  "start_date_local": "2021-01-31T11:45:35Z",
  "timezone": "(GMT+01:00) Europe/Copenhagen",
  "utc_offset": 3600,
  "location_city": null,
  "location_state": null,
  "location_country": null,
  "achievement_count": 1,
  "kudos_count": 2,
  "comment_count": 0,
  "athlete_count": 1,
  "photo_count": 0,
  "map": {
    "id": "a4711066200",
    "summary_polyline": "mn~rIq~nkAI}@Fk@f@wBn@gBJwDEg@cA[qAHIi@@mDUu@uAHaC{@eA}BMkE}G}GoCoDoA_@{FgIMY[_Do@gAmByBuCwHuAwEcC_GcAcBAg@_@kABe@i@i@k@}A_BeCmBoEkAkBmDoXmH{LcFeIaBiB{HsLiAuA}@q@iBqCuH{GcAa@qDS_BeAaENORWhAiBlAsJqB\\gCAa@VAMWSCeDPeAMgEd@mCj@{ArAkGSoCd@q@q@k@Dq@c@sAaBy@gBc@sCAuAoCHi@UMqE@kKOwFi@QeAm@Gm@qCu@_B_AyE_Bs@i@_Dk@_BaAm@s@yBeDmBuDuAoBoBwAY_A{BcDg@wA_AcBsEgH}@{@`A}ENuAUqAaB{EOeBF}EMMiMAyAdGKHo@g@_@z@iGyHJb@qAbDc@bCgBrB_@`CaA~AsA`EqClEi@B]tAkExDoAzA}@dB?bAh@zBn@jArAzE@jA|@fJhA`G?v@Ox@vA|BgC~KgBvFe@tCo@pB]zB{@`CqApEYdCkBjIgBdHe@lAgCtLyB|HNzCRFCd@yAnAc@j@|Aq@|@aBGh@aB~Cs@~BuAhHBlCi@lACd@FlBr@`JVvBH`C\\zCDpBWdCmAhFc@zIFTl@Tl@t@bB?tBj@pACv@`@U`@kAMr@XU~@IfAbAvCn@vCn@dHDvEOlDsAjG[|FzCdDbHjBXv@j@`@RhBmA~TOzGHxEp@`D`AxC`AhC\\XNb@@|@lCzL\\r@f@vBj@hGl@rEp@pArC|BjBb@vBe@p@JvDeCf@r@n@lDx@ClBf@tDdDVn@NrBo@bDBrAfArFb@lAh@v@pB`B^c@|BmI`ByL`BhAl@]n@qBTY\\?hAnA`@Q`CcLDcDfFqXbABpAjAv@[r@f@~AaBHkAUe@Ci@b@oEtEmRhDiIjGgL\\iAT[dAMDSi@sDB]lCmClC]r@g@`F_@F]OkC\\bAFlBPNlJONU@sCVcB_@e@EU?m@R]pHkAbCm@Lr@MxBF`DH|@^NpAiGPyCz@yBw@bBUbC{@`FIpBVG|AqFh@GtPxCtA`@p@l@L^fJjAhCk@~@_Bl@YbEVlK~AlFJpCe@hA{@nAYfAbA|B~@l@n@t@~At@r@`AvBfHe@z@JDr@dAXp@BdDYTNF^?fCH`@`Fj@nF_@zBLlB[`DaArAKpBu@v@u@t@U",
    "resource_state": 2
  },
  "trainer": false,
  "commute": false,
  "manual": false,
  "private": false,
  "visibility": "everyone",
  "flagged": false,
  "gear_id": "g7431700",
  "start_latlng": [
    55.7,
    12.53
  ],
  "end_latlng": [
    55.7,
    12.53
  ],
  "average_speed": 2.634,
  "max_speed": 7.8,
  "average_cadence": 83.2,
  "has_heartrate": true,
  "average_heartrate": 145.5,
  "max_heartrate": 207,
  "heartrate_opt_out": false,
  "display_hide_heartrate_option": true,
  "elev_high": 46,
  "elev_low": -1.4,
  "upload_id": 5029429221,
  "upload_id_str": "5029429221",
  "external_id": "6016ad564640bc32e438dc94.fit",
  "from_accepted_tag": false,
  "pr_count": 0,
  "total_photo_count": 0,
  "has_kudoed": false
}