{
  "resource_state": 2,
  "athlete": {
    "id": 23558655,
    "resource_state": 1
  },
  "name": "Morning Run",
  "distance": 21198.8,
  "moving_time": 6988,
  "elapsed_time": 7054,
  "total_elevation_gain": 83,
  "type": "Run",
  "sport_type": "Run",
  "workout_type": null,
  "device_name": "Garmin fēnix 6 Pro",
  "id": 6021402462,
  "start_date": "2021-09-26T08:38:30Z",
  "start_date_local": "2021-09-26T10:38:30Z",
  "timezone": "(GMT+01:00) Europe/Copenhagen",
  "utc_offset": 7200,
  "location_city": null,
  "location_state": null,
  "location_country": null,
  "achievement_count": 1,
  "kudos_count": 3,
  "comment_count": 0,
  "athlete_count": 1,
  "photo_count": 0,
  "map": {
    "id": "a6021402462",
    "summary_polyline": "if~rI}znkAp@p@xAdCf@Df@~@|AzAb@l@^lAfA?`A`AlArC\\pAJjANJrA`Fz@|A|AjHJXJSb@I?aCVeC|@]dA@XYr@^h@rBx@nGrAxEb@lCxAnE`AzBnCtEJdAfA`C|AbFhD`GfBnELxA~CdObB|JbAjN`@xKl@xMb@|D`AfDLvBdAbBl@|ATRhAAtBnAp@~Bt@bBl@~BpB|Dd@rCfAlDLbAN|CpD~GfAZrDlFbCtBz@TvAdAdGzCrD|Et@zAh@~ALxBx@nA|BtAEh@y@rBe@nCPf@|@|HjBbHbApA`@vBBnAUbDm@vAuDtCgDdB[\\_BzC}FzF{BdHqBbF}FhC_IvFsB`AqAV{FNcDc@wFvEoElGkDrDe@z@_@NSS{B~@iAH}@_@eDVoCzBcLlLuA`AwCFkAf@mHs@uJp@cDIuBg@_@JuA|AW|@WlDg@dJsBlJa@xDi@xBeBzDeAlBa@`@qBlA_APWe@YGcAt@sCcHyByDeI{L_@W{AH]k@Ss@GsBm@kDcA_D_By@qB]a@cACi@iBuC{@oFm@mBuHcGe@m@M]Y_EUu@s@m@_@u@iG_BqIcDoAAcFw@iHyB^mJn@sIKyAJ_@zBiAP_@TeBaA}EkAaD}@{E{@w@mBw@_@g@Q{AKaE[eBi@yBaBiE_AeFa@eDI{@DcCt@y@Tl@?bAUBU[eCgEk@oEYqIr@mFjCkWlCiLu@cDKgATsGB{EU}Ja@_EEeB^qGpByORgD|@cERuIAsHNyEg@}D\\oIFsGX}I?{GIy@OBs@tA}AvAc@HuC{@cAmAuDsAa@]Uu@qB_LIeCW_AWiEJ{B_AsHCaI\\sMQwBEcEWa@\\aFx@_Ht@oBRoCRm@t@Yl@iArDwAnBmAdAcAp@wAVmBA_AC_AW]KuA\\_El@eDlA}CPaAd@q@CyAi@g@IqEoCeHq@V{DwHi@kBa@qEv@}AnCmBzAYjBwAdDk@Ib@EhDf@lDh@bDrCtIV~B@lC[nEB|FcAdDvCzCvEzGZPXt@~@O|@yArD{Bd@q@vBcB`Ag@VJl@Uv@u@jByBv@K`@fAh@t@bAhDZXdC_AbCIdBp@lAnBt@h@J|@hDvL~AjEhBhMtAcCb@e@h@UfDyD^EV\\f@IjBxCnAn@vBJbErA~BLfBf@z@t@KdDJTfAf@v@DnDa@t@LCxB{@~CS|DDn@",
    "resource_state": 2
  },
  "trainer": false,
  "commute": false,
  "manual": false,
  "private": false,
  "visibility": "everyone",
  "flagged": false,
  "gear_id": "g7431711",
  "start_latlng": [
    55.7,
    12.53
  ],
  "end_latlng": [
    55.7,
    12.53
  ],
  "average_speed": 3.034,
  "max_speed": 5.2,
  "average_cadence": 88.9,
  "average_temp": 23,
  "has_heartrate": true,
  "average_heartrate": 150.2,
  "max_heartrate": 172,
  "heartrate_opt_out": false,
  "display_hide_heartrate_option": true,
  "elev_high": 37.4,
  "elev_low": 7.4,
  "upload_id": 6399785409,
  "upload_id_str": "6399785409",
  "external_id": "garmin_push_7556219482",
  "from_accepted_tag": false,
  "pr_count": 0,
  "total_photo_count": 0,
  "has_kudoed": false
}