{
  "resource_state": 2,
  "athlete": {
    "id": 23558655,
    "resource_state": 1
  },
  "name": "Morning Run",
  "distance": 10394.9,
  "moving_time": 3265,
  "elapsed_time": 3288,
  "total_elevation_gain": 46,
  "type": "Run",
  "sport_type": "Run",
  "workout_type": 0,
  "device_name": "Garmin fēnix 6 Pro",
  "id": 6050394282,
  "start_date": "2021-10-02T06:10:43Z",
  "start_date_local": "2021-10-02T08:10:43Z",
  "timezone": "(GMT+01:00) Europe/Copenhagen",
  "utc_offset": 7200,
  "location_city": null,
  "location_state": null,
  "location_country": null,
  "achievement_count": 1,
  "kudos_count": 3,
  "comment_count": 0,
  "athlete_count": 1,
  "photo_count": 0,
  "map": {
    "id": "a6050394282",
    "summary_polyline": "mm~rIg{nkASJQEISEa@?Mg@FO^GBGQQEu@~@a@lAYDc@T]BOO_@Ac@UCGGJUdAMHgAPMJy@Vg@F}@^]CQFuCKe@FQImAAgASu@?IDMXQHC?M[Qe@EB_@KYc@M@Q]y@Cg@`AMKSCOSO@yAj@s@\\y@Jq@Ec@^_@DaBU{BL}@NyAd@{ATGH_A`@OfA[bBa@x@i@xASVaBL}@V}@HUVA`@^pH?fAB|@@jA?nARbGD~BQ|@U^aAdAQh@[Nm@H_@Ni@Ga@]]kAcAqFKmAQ_AMaBIg@Y{@o@eDc@}@UqAU{@_@s@Ww@qAmCe@]I@U~@Gn@cBzDCn@Bv@Jf@\\j@v@~ARdALrA@p@ChAOx@Qb@}AdCkA`Ak@r@YFc@`@c@Pw@n@e@P]j@@nCGjHGjC?dFOdG@tCGdACpBV`AV^f@JvA?hAd@x@JbA`@v@n@f@Tn@Nd@XnAvAB`AG`Aa@rCS~@]|DA~@EbAKpAChA@nAIhAH|Cv@vFJbAR`DBnBFfAAf@Mv@KxDIdAENOjBOh@Wf@[nBc@nAOpAL\\v@p@bApAvClEhCfEn@vAd@r@Zn@Xt@^r@lB~Jr@`DXhAh@`BRz@^dAx@zC`AxCt@f@dBp@d@F`@j@~@dB~A~Ax@tA`BfD^j@nBtBrDxAl@`@f@JpAKj@WhASf@f@RJp@DXYPs@@SOyBi@iCW{@oAqAaCyA{@w@i@_AWo@Uy@QeAG_AAqA@cAZuGAgAImASeAg@_Aa@_@m@]m@m@i@cAa@eAMcCD}Bx@cEdBqDb@cBBsALu@h@Yn@AnFk@@m@C_GDg@TKRa@P{@P_CP_Ad@c@d@S\\D\\g@`@w@DU?[Q{A_@gGOcAQs@Em@Y{B?y@IgAi@oCKcB^wAPaA^kDPcC^oCFeAJa@d@{@d@cB\\u@Pm@z@eBLe@R_@\\c@Z}@\\SJUHqA@mCLq@J_AJu@ZcA?e@NsBTeAHq@LoCf@gCK_B@y@DYPm@HcA\\}AOaAp@eFb@aBVs@p@gBTa@Lw@Ne@NYP_AV]Xo@D[z@oDz@}AZ_@b@u@TeBJKX}@D]DgAXw@j@qCX_@~@qC\\u@J_@\\q@",
    "resource_state": 2
  },
  "trainer": false,
  "commute": false,
  "manual": false,
  "private": false,
  "visibility": "everyone",
  "flagged": false,
  "gear_id": "g6163873",
  "start_latlng": [
    55.7,
    12.53
  ],
  "end_latlng": [
    55.7,
    12.53
  ],
  "average_speed": 3.184,
  "max_speed": 6.8,
  "average_cadence": 93.1,
  "average_temp": 21,
  "has_heartrate": true,
  "average_heartrate": 153,
  "max_heartrate": 176,
  "heartrate_opt_out": false,
  "display_hide_heartrate_option": true,
  "elev_high": 32.8,
  "elev_low": 11.2,
  "upload_id": 6430197112,
  "upload_id_str": "6430197112",
  "external_id": "garmin_push_7588167812",
  "from_accepted_tag": false,
  "pr_count": 1,
  "total_photo_count": 0,
  "has_kudoed": false
}