{
  "resource_state": 2,
  "athlete": {
    "id": 23558655,
    "resource_state": 1
  },
  "name": "Afternoon Run",
  "distance": 12005.8,
  "moving_time": 4062,
  "elapsed_time": 4157,
  "total_elevation_gain": 152,
  "type": "Run",
  "sport_type": "Run",
  "workout_type": 0,
  "device_name": "Garmin fēnix 6 Pro",
  "id": 8298776945,
  "start_date": "2022-12-27T16:19:29Z",
  "start_date_local": "2022-12-27T16:19:29Z",
  "timezone": "(GMT+00:00) Europe/Lisbon",
  "utc_offset": 0,
  "location_city": null,
  "location_state": null,
  "location_country": null,
  "achievement_count": 4,
  "kudos_count": 1,
  "comment_count": 0,
  "athlete_count": 1,
  "photo_count": 0,
  "map": {
    "id": "a8298776945",
    "summary_polyline": "qqqkF|utv@MbBJ{@PMPVHj@Ep@GNFfCXnEZxA`At@NPpAl@nCzEf@j@lAl@jAVxAF`C[nBg@p@AzBg@b@[d@g@RsAJ]TU\\Gl@?HJPDZAr@Mn@Yz@Ib@B`Al@\\\\Pb@\\PnAcArFkFX[DIAI`@YR?FN?v@FrA_@~BQ`@[\\sBrAELX~@v@jARh@Hj@zCg@rACTSXa@p@k@rB}@f@InA@\\PT`@b@Zd@O\\s@Fg@b@e@b@u@t@[l@i@Xw@DgAg@sAWiD_@mB?c@HU^Ch@NjABzAo@fAEfA{@lBsBDM?y@H_@TW^SNWn@aCLWPMx@?xAg@zAoARyACWo@oAuBe@m@F[SyAl@o@Me@`@qBrB[V[HE?e@]oBMYF]Ac@JcA?g@HQWC{CGw@?s@QiAKmA?k@g@}CWcC?g@LU^YDQAOGQsAqBsAgBOKy@EqIPaDEiDTOE]PO@OPSEaBHOQK_@Go@BWg@wAC{@Ki@_@s@KGQDYUWCQMO_@AQD[WuAg@s@_AGQJELWT[r@CTu@nCSnASZm@PsCk@aFiAy@cAWk@c@oAGEYAu@l@WFu@Ei@SwAAuAXgAj@k@HwBNeBdAc@d@MDsA`A_Bl@y@Jg@`@aA\\KPEp@c@|AqAk@UXOb@g@f@m@lA?|@GlAQt@]j@i@d@[b@@bAQt@Yx@k@`@gAZm@BcAEk@i@o@c@Ym@_@qAGk@@g@MyAPd@Mt@Ch@HZLlAPt@bAjBHhAQ`A?h@|@VvAGp@KpA_@dAINDNVF~@DPZ`@Ed@B`@Vr@Yz@{Ad@iBnAWb@Mj@GxABj@H\\f@rAh@|@v@~ADn@R^?Je@`@IPTz@|AxAf@Jh@C`@i@XeA\\g@tA_D`AoAPk@Ve@p@]T_@Na@Jc@AuAQu@s@iAaAk@m@?e@H{At@WDYV]j@Ef@AbBMtBa@|AIx@I`@]~@MR_@Pa@Z@z@b@d@lAv@z@@RCZUf@{AT_@jAwCpAuBBUd@Wj@i@Xk@Ru@D}@SqA}@mA[Ue@S_ADsBbAc@FY^EJWxFU`B[vAm@xAm@d@a@n@`@bAvAx@\\Ff@?lAg@v@iC",
    "resource_state": 2
  },
  "trainer": false,
  "commute": false,
  "manual": false,
  "private": false,
  "visibility": "everyone",
  "flagged": false,
  "gear_id": "g12480911",
  "start_latlng": [
    38.76,
    -9.12
  ],
  "end_latlng": [
    38.76,
    -9.12
  ],
  "average_speed": 2.956,
  "max_speed": 4.492,
  "average_cadence": 85.6,
  "average_temp": 23,
  "has_heartrate": true,
  "average_heartrate": 149.9,
  "max_heartrate": 178,
  "heartrate_opt_out": false,
  "display_hide_heartrate_option": true,
  "elev_high": 110.4,
  "elev_low": 52.8,
  "upload_id": 8896622835,
  "upload_id_str": "8896622835",
  "external_id": "garmin_ping_252715230450",
  "from_accepted_tag": false,
  "pr_count": 1,
  "total_photo_count": 0,
  "has_kudoed": false
}