{
  "resource_state": 2,
  "athlete": {
    "id": 23558655,
    "resource_state": 1
  },
  "name": "Afternoon Run",
  "distance": 14035,
  "moving_time": 4550,
  "elapsed_time": 4574,
  "total_elevation_gain": 58,
  "type": "Run",
  "sport_type": "Run",
  "workout_type": null,
  "device_name": "Garmin fēnix 6 Pro",
  "id": 8450252670,
  "start_date": "2023-01-25T14:58:42Z",
  "start_date_local": "2023-01-25T15:58:42Z",
  "timezone": "(GMT+01:00) Europe/Copenhagen",
  "utc_offset": 3600,
  "location_city": null,
  "location_state": null,
  "location_country": null,
  "achievement_count": 1,
  "kudos_count": 2,
  "comment_count": 0,
  "athlete_count": 1,
  "photo_count": 0,
  "map": {
    "id": "a8450252670",
    "summary_polyline": "um~rIkfokALy@N[BS@u@J}ACuALuBDMi@@{@OcAFkAg@qBF_Cg@YcAwCGeCe@I]@aDKyDBeATsAVi@EO_@UE_@e@u@w@_@OSi@Co@g@c@k@_B}@e@y@g@{AMMOa@McAUqAi@qBeB_B]c@{@oBUo@s@oCaAkCoBwEWqA]aAc@wBKKe@gAKq@M]m@}@e@aAeAyAe@aB{AyC{@uAAK_@m@yA{COiAOgEIiCF_A?i@Qs@Wq@m@u@c@}@sCoEm@s@Yu@sCwEqEkGqB_De@_AmCcDyAqASo@S]WKc@aA{@m@gBmBe@]a@i@y@Yi@_@[_@a@AqAf@i@Cg@O]_@M[c@[oAAeBJOIQVGl@Up@]BcAv@qAMsCgA{BOGP?j@SjCCnAStBChBOhAS~CU~H?nALhC@`H^zI@`FL~FJfAE`DBfBLzDH`@LvBfAtEz@vBZ`@fAfC^n@tA~Ax@p@T\\jAp@Z`ATb@f@DX`@v@j@`D`Df@t@@HEn@Ml@U\\Sv@SvAWp@]pBKr@QvGIpAQhAm@`B{CpB}CvA_AbAc@VIVGhAGNA`AY~BEKSr@WPc@UiAHa@`@c@TwALYPUPk@rCM\\T~AFtBnFo@^OXHJv@DlDJpB?|CGdA?fAIp@I~BOrJHlAl@lER`EX|CPzEj@lDPlBOh@SJ]CuBRm@C_@FKVs@rHIhBN`Ad@rETbAj@l@z@|Al@x@bBfA\\p@tBvA`@`@`CzAbChB|At@pA~@f@d@Rj@PTlBN`Dj@|AfAzCbBjB~AHl@Af@[vB_@fDMtCS~@[lJ?r@NdCx@zGJnALvFCzENlB`AnE`A|Fh@zB\\pBLXVBb@KjAo@x@]pBgBzDeFpAsAFYAO[q@Me@i@wC[aECaABy@TmCP_A^sA|BmGd@oC?e@MyD_@aBQe@]]aBU}Ak@eCa@y@e@o@aAQ{@k@mF@eDZ_FZeA\\cBf@kDb@iFJmC@oHFsAB{CTkBCuELyMAcFBwOJc@`AQbFkA`BmDZiAHu@R[`@OTUrDeApB[NFz@Ix@DAu@f@JZPhANnALr@KjAD^M~@Hn@K^HnAQVH\\C`@]PAjCRz@V^Uh@BjAO|@D`@Nf@WhAJRe@`@Wz@Bb@UXDp@[R@",
    "resource_state": 2
  },
  "trainer": false,
  "commute": false,
  "manual": false,
  "private": false,
  "visibility": "everyone",
  "flagged": false,
  "gear_id": "g10893777",
  "start_latlng": [
    55.7,
    12.53
  ],
  "end_latlng": [
    55.7,
    12.53
  ],
  "average_speed": 3.085,
  "max_speed": 5.887,
  "average_cadence": 88.3,
  "average_temp": 14,
  "has_heartrate": true,
  "average_heartrate": 143.7,
  "max_heartrate": 181,
  "heartrate_opt_out": false,
  "display_hide_heartrate_option": true,
  "elev_high": 33.8,
  "elev_low": 10.2,
  "upload_id": 9066087035,
  "upload_id_str": "9066087035",
  "external_id": "garmin_ping_257018943679",
  "from_accepted_tag": false,
  "pr_count": 1,
  "total_photo_count": 0,
  "has_kudoed": false
}