{
  "resource_state": 2,
  "athlete": {
    "id": 23558655,
    "resource_state": 1
  },
  "name": "Morning Run",
  "distance": 7178.2,
  "moving_time": 2572,
  "elapsed_time": 2663,
  "total_elevation_gain": 80,
  "type": "Run",
  "sport_type": "Run",
  "workout_type": null,
  "device_name": "Garmin fēnix 6 Pro",
  "id": 8861199072,
  "start_date": "2023-04-06T23:32:28Z",
  "start_date_local": "2023-04-07T07:32:28Z",
  "timezone": "(GMT+08:00) Asia/Manila",
  "utc_offset": 28800,
  "location_city": null,
  "location_state": null,
  "location_country": null,
  "achievement_count": 1,
  "kudos_count": 1,
  "comment_count": 0,
  "athlete_count": 1,
  "photo_count": 0,
  "map": {
    "id": "a8861199072",
    "polyline": "ednxAymuaV_@MOKSLI@YEE?GJCR@TCRGDMT@TRT?DO`@YpAAp@DF@NI^IN?Lb@LT@JDr@?GRIHGCDONKJo@\\i@H?@CF[Xm@JKB@@EIM?ML]KcAI]S_@QKo@BBOEAKBSMMCODITIt@CBKPDTSv@@vAG\\GFGLG\\Mf@?LRABDlBJHJD?BGA?QgNEHQIKNM^e@bAER@NKRAJ@|AFd@EJGXGLCRKR@H?Rn@R|@Fr@ZAN^wND\\@WYG]HYBMAMBCBBDUF?NM\\MJMj@EvABn@Ed@ERMJQd@H`@VF\\h@f@DJCZFV?JH\\l@fAiMKWC]OOMCEGYDg@EYHMb@BHCn@KZQjAKd@E`AWr@QNWh@ZH\\NfAVd@RNPHBv@_BAQGUVHOS?AOW[yGa@CY?SECG@ZS@I\\IP@^Gd@Ih@GJUzAABWHOJANGD?D[j@RH|@Pn@\\pAVN?bBqOg@MIB_@E?DQDUGMABn@EHWR@^[t@EVQ`@Kh@KTeAd@a@r@EXDF^LPTZN|A\\\\JD?NT`@]z@iBBPJHBGIC@OOm@?_@BU[qDU_@MAIDMCY@g@IGPC@?RITGJKDGJBl@CXS`@IXEn@@\\m@VGFERE@CJC@DNb@LXX`@DVJfAL^X@AFF?F^K|@gOQNaBDa@CQBEGIHELKLO`@?FDJC^GL?JKJK`@CnA@BIHQDMPOLML[@?Bd@Lz@p@XJt@f@XH`@VDFFABQe@iDSs@j@sEj@c@OSIEYCCGJ?MIu@UOAAFDB?B[XMj@@v@y@lBE`@W^YR]HGLSJ@F`@f@D?RJZZdCxAZ@TF|AkBFQB@BEBMGGKCWwCEUOHcAT]BMIJi@GS@ELWWg@KBCFOBBDANFHAl@EXOb@In@Aj@ELQPIRi@\\@Dl@N|@`@x@JXNLEVDFA?a@DOb@c@CI?IfA_B?M",
    "resource_state": 3,
    "summary_polyline": "ednxAymuaV_@MOKSLI@YEE?GJCR@TCRGDMT@TRT?DO`@YpAAp@DF@NI^IN?Lb@LT@JDr@?GRIHGCDONKJo@\\i@H?@CF[Xm@JKB@@EIM?ML]KcAI]S_@QKo@BBOEAKBSMMCODITIt@CBKPDTSv@@vAG\\GFGLG\\Mf@?LRABDlBJHJD?BGA?QgNEHQIKNM^e@bAER@NKRAJ@|AFd@EJGXGLCRKR@H?Rn@R|@Fr@ZAN^wND\\@WYG]HYBMAMBCBBDUF?NM\\MJMj@EvABn@Ed@ERMJQd@H`@VF\\h@f@DJCZFV?JH\\l@fAiMKWC]OOMCEGYDg@EYHMb@BHCn@KZQjAKd@E`AWr@QNWh@ZH\\NfAVd@RNPHBv@_BAQGUVHOS?AOW[yGa@CY?SECG@ZS@I\\IP@^Gd@Ih@GJUzAABWHOJANGD?D[j@RH|@Pn@\\pAVN?bBqOg@MIB_@E?DQDUGMABn@EHWR@^[t@EVQ`@Kh@KTeAd@a@r@EXDF^LPTZN|A\\\\JD?NT`@]z@iBBPJHBGIC@OOm@?_@BU[qDU_@MAIDMCY@g@IGPC@?RITGJKDGJBl@CXS`@IXEn@@\\m@VGFERE@CJC@DNb@LXX`@DVJfAL^X@AFF?F^K|@gOQNaBDa@CQBEGIHELKLO`@?FDJC^GL?JKJK`@CnA@BIHQDMPOLML[@?Bd@Lz@p@XJt@f@XH`@VDFFABQe@iDSs@j@sEj@c@OSIEYCCGJ?MIu@UOAAFDB?B[XMj@@v@y@lBE`@W^YR]HGLSJ@F`@f@D?RJZZdCxAZ@TF|AkBFQB@BEBMGGKCWwCEUOHcAT]BMIJi@GS@ELWWg@KBCFOBBDANFHAl@EXOb@In@Aj@ELQPIRi@\\@Dl@N|@`@x@JXNLEVDFA?a@DOb@c@CI?IfA_B?M"
  },
  "trainer": false,
  "commute": false,
  "manual": false,
  "private": false,
  "visibility": "everyone",
  "flagged": false,
  "gear_id": "g10893777",
  "start_latlng": [],
  "end_latlng": [],
  "average_speed": 2.791,
  "max_speed": 7.698,
  "average_cadence": 86.1,
  "average_temp": 31,
  "has_heartrate": true,
  "average_heartrate": 135.3,
  "max_heartrate": 149,
  "heartrate_opt_out": false,
  "display_hide_heartrate_option": true,
  "elev_high": 118,
  "elev_low": 61.8,
  "upload_id": 9508103369,
  "upload_id_str": "9508103369",
  "external_id": "garmin_ping_268419137067",
  "from_accepted_tag": false,
  "pr_count": 0,
  "total_photo_count": 0,
  "has_kudoed": false
}